odoo/addons/shopinvader_payment/README.rst
odoo/addons/shopinvader_payment/__init__.py
odoo/addons/shopinvader_payment/__manifest__.py
odoo/addons/shopinvader_payment/components/__init__.py
odoo/addons/shopinvader_payment/components/payment_transaction_event_listerner.py
odoo/addons/shopinvader_payment/i18n/shopinvader_payment.pot
odoo/addons/shopinvader_payment/models/__init__.py
odoo/addons/shopinvader_payment/models/payment_transaction.py
odoo/addons/shopinvader_payment/models/sale_order.py
odoo/addons/shopinvader_payment/models/shopinvader_backend.py
odoo/addons/shopinvader_payment/models/shopinvader_payment.py
odoo/addons/shopinvader_payment/readme/CONTRIBUTORS.rst
odoo/addons/shopinvader_payment/readme/DESCRIPTION.rst
odoo/addons/shopinvader_payment/security/ir.model.access.csv
odoo/addons/shopinvader_payment/services/__init__.py
odoo/addons/shopinvader_payment/services/abstract_payable_sale.py
odoo/addons/shopinvader_payment/services/cart.py
odoo/addons/shopinvader_payment/services/invader_payment_service.py
odoo/addons/shopinvader_payment/services/payment_token.py
odoo/addons/shopinvader_payment/static/description/index.html
odoo/addons/shopinvader_payment/tests/__init__.py
odoo/addons/shopinvader_payment/tests/test_payment.py
odoo/addons/shopinvader_payment/views/backend_view.xml
odoo/addons/shopinvader_payment/views/shopinvader_menu.xml
odoo/addons/shopinvader_payment/views/shopinvader_payment_view.xml
odoo12_addon_shopinvader_payment-12.0.3.0.0.dist-info/METADATA
odoo12_addon_shopinvader_payment-12.0.3.0.0.dist-info/WHEEL
odoo12_addon_shopinvader_payment-12.0.3.0.0.dist-info/top_level.txt
odoo12_addon_shopinvader_payment-12.0.3.0.0.dist-info/RECORD
