Metadata-Version: 2.1
Name: odoo12-addon-shopinvader-payment
Version: 12.0.3.0.0
Summary: Payment integration for Shopinvader
Home-page: https://github.com/shopinvader/odoo-shopinvader-payment
Author: Akretion
License: AGPL-3
Platform: UNKNOWN
Classifier: Programming Language :: Python
Classifier: Framework :: Odoo
Classifier: License :: OSI Approved :: GNU Affero General Public License v3
Requires-Python: >=3.5
Requires-Dist: cerberus
Requires-Dist: odoo12-addon-account-payment-mode
Requires-Dist: odoo12-addon-account-payment-sale
Requires-Dist: odoo12-addon-component-event
Requires-Dist: odoo12-addon-invader-payment
Requires-Dist: odoo12-addon-onchange-helper
Requires-Dist: odoo12-addon-sale-automatic-workflow-payment-mode
Requires-Dist: odoo12-addon-shopinvader
Requires-Dist: odoo (<12.1dev,>=12.0a)
Requires-Dist: unidecode
